{
  "elements": [
    {
      "type": "text",
      "body": "<p>\n    Znane nam i stosunkowo często używane jednostki miary długości to:\n</p>"
    },
    {
      "type": "text",
      "body": "<ul>\n<li>milimetr,</li>\n<li>centymetr,</li>\n<li>decymetr,</li>\n<li>metr,</li>\n<li>kilometr.</li>\n</ul>"
    },
    {
      "type": "image",
      "media_src": "static/jednostki_dlugosci.png",
      "alt": "",
      "figcaption": ""
    },
    {
      "type": "text",
      "body": "<p>\n        Powyższy schemat rozumiemy tak, że:\n    </p>"
    },
    {
      "type": "html",
      "flagged": true,
      "raw": "<table class=\"my_table_noborder\">\n<tr>\n<td>\\(1\\,\\text{cm}=10\\,\\text{mm}\\)</td>\n<td></td>\n<td>\\(1\\,\\text{dm}=10\\,\\text{cm}\\)</td>\n<td></td>\n<td>\\(1\\,\\text{m}=10\\,\\text{dm}\\)</td>\n</tr>\n<tr>\n<td></td>\n<td colspan=\"3\">\\(1\\,\\text{km}=1000\\,\\text{m}\\)</td>\n<td></td>\n</tr>\n<tr>\n<td>i odwrotnie:</td>\n<td colspan=\"4\"></td>\n</tr>\n<tr>\n<td>\\(1\\,\\text{mm}=0,1\\,\\text{cm}\\)</td>\n<td></td>\n<td>\\(1\\,\\text{cm}=0,1\\,\\text{dm}\\)</td>\n<td></td>\n<td>\\(1\\,\\text{dm}=0,1\\,\\text{m}\\)</td>\n</tr>\n<tr>\n<td></td>\n<td colspan=\"3\">\\(1\\,\\text{m}=0,001\\,\\text{km}\\)</td>\n<td></td>\n</tr>\n</table>",
      "reason": "table uses rowspan/colspan"
    },
    {
      "type": "text",
      "body": "<p class=\"question\"></p>"
    },
    {
      "type": "text",
      "body": "\n<p>\n                    Uzupełnij.\n                </p>\n<ol class=\"bold\">\n<li>\n                        \\(2\\,\\text{m}=\\)<input class=\"table_input\" placeholder=\"wpisz\" type=\"text\"/>\\(\\,\\text{dm}\\)\n                    </li>\n<li>\n                        \\(1\\,\\text{m}=\\)<input class=\"table_input\" placeholder=\"wpisz\" type=\"text\"/>\\(\\,\\text{mm}\\)\n                    </li>\n<li>\n                        \\(3\\,\\text{dm}=\\)<input class=\"table_input\" placeholder=\"wpisz\" type=\"text\"/>\\(\\,\\text{mm}\\)\n                    </li>\n<li>\n                        \\(15\\,\\text{m}=\\)<input class=\"table_input\" placeholder=\"wpisz\" type=\"text\"/>\\(\\,\\text{mm}\\)\n                    </li>\n<li>\n                        \\(2\\,\\text{km}=\\)<input class=\"table_input\" placeholder=\"wpisz\" type=\"text\"/>\\(\\,\\text{cm}\\)\n                    </li>\n</ol>\n"
    },
    {
      "type": "text",
      "body": "\n            Świetnie!\n        "
    },
    {
      "type": "text",
      "body": "<p class=\"question\"></p>"
    },
    {
      "type": "text",
      "body": "\n<p>\n                    Uzupełnij.\n                </p>\n<ol class=\"bold\">\n<li>\n                        \\(1\\,\\text{cm}=\\)<input class=\"table_input\" placeholder=\"wpisz\" type=\"text\"/>\\(\\,\\text{m}\\)\n                    </li>\n<li>\n                        \\(5\\,\\text{dm}=\\)<input class=\"table_input\" placeholder=\"wpisz\" type=\"text\"/>\\(\\,\\text{m}\\)\n                    </li>\n<li>\n                        \\(13\\,\\text{m}=\\)<input class=\"table_input\" placeholder=\"wpisz\" type=\"text\"/>\\(\\,\\text{km}\\)\n                    </li>\n<li>\n                        \\(20\\,\\text{cm}=\\)<input class=\"table_input\" placeholder=\"wpisz\" type=\"text\"/>\\(\\,\\text{km}\\)\n                    </li>\n<li>\n                        \\(25\\,\\text{mm}=\\)<input class=\"table_input\" placeholder=\"wpisz\" type=\"text\"/>\\(\\,\\text{dm}\\)\n                    </li>\n</ol>\n"
    },
    {
      "type": "text",
      "body": "\n            Brawo!\n        "
    },
    {
      "type": "text",
      "body": "<p>\n    Z jednostkami kwadratowymi jest trochę inaczej.\n</p>"
    },
    {
      "type": "image",
      "media_src": "static/jednostka_kwadratowa_wstep.png",
      "alt": "",
      "figcaption": ""
    },
    {
      "type": "text",
      "body": "<p>\n    Służą do mierzenia pola, więc muszą uwzględniać dwa wymiary: zarówno długość, jak szerokość. \n</p>"
    },
    {
      "type": "text",
      "body": "<p>\n    Takie jednostki to:\n</p>"
    },
    {
      "type": "text",
      "body": "<ul>\n<li>milimetr <i>kwadratowy</i>,</li>\n<li>centymetr <i>kwadratowy</i>,</li>\n<li>decymetr <i>kwadratowy</i>,</li>\n<li>metr <i>kwadratowy</i>,</li>\n<li>kilometr <i>kwadratowy</i>.</li>\n</ul>"
    },
    {
      "type": "text",
      "body": "<p>\n    Przyjrzyjmy im się bliżej. \n</p>"
    }
  ],
  "fully_mapped": false,
  "seed_hash": "7978ceff245475a8fc610e98508d2f7ce2f1ff877bcb8ee3a809d457ae53a235"
}