{
  "elements": [
    {
      "type": "text",
      "body": "<p><strong>Zadanie</strong></p>"
    },
    {
      "type": "text",
      "body": "<p>Poniższym aplecie możesz:</p>"
    },
    {
      "type": "text",
      "body": "<ul>\n<li>\n                przesuwać punkty kończące niebieski i czerwony przedział,\n            </li>\n<li>\n                klikać na nie, by zmieniać ich należenie do przedziałów\n            </li>\n<li>\n                wybrać, jakiego działania wynik chcesz zobaczyć (sumę, iloczyn, czy różnicę).\n            </li>\n</ul>"
    },
    {
      "type": "text",
      "body": "\n            Możesz użyć apletu, by poćwiczyć działania na przedziałach, na przykład w ten sposób, żeby z użyciem różnych działań uzyskać następujące wyniki:\n        "
    },
    {
      "type": "text",
      "body": "<p>(Dla swojej wygody możesz zazanczyć to, co już zrobisz.)</p>"
    },
    {
      "type": "html",
      "flagged": true,
      "raw": "<div>\n<div class=\"mark_done statement\" data-width=\"200px\">\n                \\(\\langle 3, 5)\\)\n            </div>\n<input type=\"checkbox\"/>\n</div>\n<div>\n<div class=\"mark_done statement\" data-width=\"200px\">\n                \\((-2, 4\\rangle\\)\n            </div>\n<input type=\"checkbox\"/>\n</div>\n<div>\n<div class=\"mark_done statement\" data-width=\"200px\">\n                \\(\\{2\\}\\)\n            </div>\n<input type=\"checkbox\"/>\n</div>\n<div>\n<div class=\"mark_done statement\" data-width=\"200px\">\n                \\(\\{2\\}\\cup\\{5\\}\\)\n            </div>\n<input type=\"checkbox\"/>\n</div>\n<div>\n<div class=\"mark_done statement\" data-width=\"200px\">\n                \\((-5,-1)\\cup\\langle 2,4\\rangle\\)\n            </div>\n<input type=\"checkbox\"/>\n</div>",
      "reason": "interactive_widget (Group B): mark_done"
    },
    {
      "type": "iframe",
      "url": "https://www.geogebra.org/material/iframe/id/rwkezkm2/width/800/height/320/border/888888/sfsb/true/smb/false/stb/false/stbh/false/ai/false/asb/false/sri/false/rc/false/ld/false/sdz/false/ctl/false",
      "title": ""
    }
  ],
  "fully_mapped": false,
  "seed_hash": "8509b6b9d9c186802de74cc2e19446c8c139f6a8f8910bee8b1c6908a08ae5ca"
}