{
  "elements": [
    {
      "type": "text",
      "body": "<p class=\"example\">\n</p>"
    },
    {
      "type": "text",
      "body": "<p>\n            Na ile sposobów możemy wybrać trzy obiekty spośród pięciu?\n        </p>"
    },
    {
      "type": "spoiler",
      "label": "przeczytaj rozwiązanie",
      "body": "\n\n<div class=\"steps\">\n<p>\n                    Oznaczmy te pięć obiektów literami: \n                    <span style=\"color: red; font-weight: bold;\">A</span>, \n                    <span style=\"color: blue; font-weight: bold;\">B</span>, \n                    <span style=\"color: green; font-weight: bold;\">C</span>, \n                    <span style=\"color: orange; font-weight: bold;\">D</span>, \n                    <span style=\"color: black; font-weight: bold;\">E</span>.\n                </p>\n<div class=\"show_next ks_button\">pokaż dalej</div>\n<div class=\"show_step\">\n<p>\n                        Czy to przypadkiem nie jest tak, że \n                    </p>\n<ul class=\"nolist\">\n<li>pierwszy obiekt wybieramy na \\(5\\) sposobów,</li>\n<li>drugi obiekt wybieramy na \\(4\\) sposoby,</li>\n<li>trzeci obiekt wybieramy na \\(3\\) sposoby?</li>\n</ul>\n</div>\n<div class=\"show_next ks_button\">pokaż dalej</div>\n<div class=\"show_step\">\n<p>\n                        Czyli odpowiedzią na to pytanie byłaby liczba \\(3\\)-wyrazowych wariacji <strong>bez powtórzeń</strong> ze zbioru \\(5\\)-elementowego?\n                    </p>\n                    \\[\n                    V_5^3=\\frac{5!}{(5-3)!}=5\\cdot 4\\cdot 3=60\n                    \\]\n                    ?\n                </div>\n<div class=\"show_next ks_button\">pokaż dalej</div>\n<div class=\"show_step\">\n<p>\n                        Nie całkiem... \n                    </p>\n<p>\n                        Dlaczego? Wypiszmy wszystkie takie wariacje:\n                    </p>\n<div class=\"table_wrapper\">\n<table class=\"my_table_noborder\">\n<tr><td>1.</td><th><span style=\"color: red;\">A</span><span style=\"color: blue;\">B</span><span style=\"color: green;\">C</span></th><th></th><td>13.</td><th><span style=\"color: blue;\">B</span><span style=\"color: red;\">A</span><span style=\"color: green;\">C</span></th><th></th><td>25.</td><th><span style=\"color: green;\">C</span><span style=\"color: red;\">A</span><span style=\"color: blue;\">B</span></th><th></th><td>37.</td><th><span style=\"color: orange;\">D</span><span style=\"color: red;\">A</span><span style=\"color: blue;\">B</span></th><th></th><td>49.</td><th><span style=\"color: black;\">E</span><span style=\"color: red;\">A</span><span style=\"color: blue;\">B</span></th></tr>\n<tr><td>2.</td><th><span style=\"color: red;\">A</span><span style=\"color: blue;\">B</span><span style=\"color: orange;\">D</span></th><th></th><td>14.</td><th><span style=\"color: blue;\">B</span><span style=\"color: red;\">A</span><span style=\"color: orange;\">D</span></th><th></th><td>26.</td><th><span style=\"color: green;\">C</span><span style=\"color: red;\">A</span><span style=\"color: orange;\">D</span></th><th></th><td>38.</td><th><span style=\"color: orange;\">D</span><span style=\"color: red;\">A</span><span style=\"color: green;\">C</span></th><th></th><td>50.</td><th><span style=\"color: black;\">E</span><span style=\"color: red;\">A</span><span style=\"color: green;\">C</span></th></tr>\n<tr><td>3.</td><th><span style=\"color: red;\">A</span><span style=\"color: blue;\">B</span><span style=\"color: black;\">E</span></th><th></th><td>15.</td><th><span style=\"color: blue;\">B</span><span style=\"color: red;\">A</span><span style=\"color: black;\">E</span></th><th></th><td>27.</td><th><span style=\"color: green;\">C</span><span style=\"color: red;\">A</span><span style=\"color: black;\">E</span></th><th></th><td>39.</td><th><span style=\"color: orange;\">D</span><span style=\"color: red;\">A</span><span style=\"color: black;\">E</span></th><th></th><td>51.</td><th><span style=\"color: black;\">E</span><span style=\"color: red;\">A</span><span style=\"color: orange;\">D</span></th></tr>\n<tr><td>4.</td><th><span style=\"color: red;\">A</span><span style=\"color: green;\">C</span><span style=\"color: blue;\">B</span></th><th></th><td>16.</td><th><span style=\"color: blue;\">B</span><span style=\"color: green;\">C</span><span style=\"color: red;\">A</span></th><th></th><td>28.</td><th><span style=\"color: green;\">C</span><span style=\"color: blue;\">B</span><span style=\"color: red;\">A</span></th><th></th><td>40.</td><th><span style=\"color: orange;\">D</span><span style=\"color: blue;\">B</span><span style=\"color: red;\">A</span></th><th></th><td>52.</td><th><span style=\"color: black;\">E</span><span style=\"color: blue;\">B</span><span style=\"color: red;\">A</span></th></tr>\n<tr><td>5.</td><th><span style=\"color: red;\">A</span><span style=\"color: green;\">C</span><span style=\"color: orange;\">D</span></th><th></th><td>17.</td><th><span style=\"color: blue;\">B</span><span style=\"color: green;\">C</span><span style=\"color: orange;\">D</span></th><th></th><td>29.</td><th><span style=\"color: green;\">C</span><span style=\"color: blue;\">B</span><span style=\"color: orange;\">D</span></th><th></th><td>41.</td><th><span style=\"color: orange;\">D</span><span style=\"color: blue;\">B</span><span style=\"color: green;\">C</span></th><th></th><td>53.</td><th><span style=\"color: black;\">E</span><span style=\"color: blue;\">B</span><span style=\"color: green;\">C</span></th></tr>\n<tr><td>6.</td><th><span style=\"color: red;\">A</span><span style=\"color: green;\">C</span><span style=\"color: black;\">E</span></th><th></th><td>18.</td><th><span style=\"color: blue;\">B</span><span style=\"color: green;\">C</span><span style=\"color: black;\">E</span></th><th></th><td>30.</td><th><span style=\"color: green;\">C</span><span style=\"color: blue;\">B</span><span style=\"color: black;\">E</span></th><th></th><td>42.</td><th><span style=\"color: orange;\">D</span><span style=\"color: blue;\">B</span><span style=\"color: black;\">E</span></th><th></th><td>54.</td><th><span style=\"color: black;\">E</span><span style=\"color: blue;\">B</span><span style=\"color: orange;\">D</span></th></tr>\n<tr><td>7.</td><th><span style=\"color: red;\">A</span><span style=\"color: orange;\">D</span><span style=\"color: blue;\">B</span></th><th></th><td>19.</td><th><span style=\"color: blue;\">B</span><span style=\"color: orange;\">D</span><span style=\"color: red;\">A</span></th><th></th><td>31.</td><th><span style=\"color: green;\">C</span><span style=\"color: orange;\">D</span><span style=\"color: red;\">A</span></th><th></th><td>43.</td><th><span style=\"color: orange;\">D</span><span style=\"color: green;\">C</span><span style=\"color: red;\">A</span></th><th></th><td>55.</td><th><span style=\"color: black;\">E</span><span style=\"color: green;\">C</span><span style=\"color: red;\">A</span></th></tr>\n<tr><td>8.</td><th><span style=\"color: red;\">A</span><span style=\"color: orange;\">D</span><span style=\"color: green;\">C</span></th><th></th><td>20.</td><th><span style=\"color: blue;\">B</span><span style=\"color: orange;\">D</span><span style=\"color: green;\">C</span></th><th></th><td>32.</td><th><span style=\"color: green;\">C</span><span style=\"color: orange;\">D</span><span style=\"color: blue;\">B</span></th><th></th><td>44.</td><th><span style=\"color: orange;\">D</span><span style=\"color: green;\">C</span><span style=\"color: blue;\">B</span></th><th></th><td>56.</td><th><span style=\"color: black;\">E</span><span style=\"color: green;\">C</span><span style=\"color: blue;\">B</span></th></tr>\n<tr><td>9.</td><th><span style=\"color: red;\">A</span><span style=\"color: orange;\">D</span><span style=\"color: black;\">E</span></th><th></th><td>21.</td><th><span style=\"color: blue;\">B</span><span style=\"color: orange;\">D</span><span style=\"color: black;\">E</span></th><th></th><td>33.</td><th><span style=\"color: green;\">C</span><span style=\"color: orange;\">D</span><span style=\"color: black;\">E</span></th><th></th><td>45.</td><th><span style=\"color: orange;\">D</span><span style=\"color: green;\">C</span><span style=\"color: black;\">E</span></th><th></th><td>57.</td><th><span style=\"color: black;\">E</span><span style=\"color: green;\">C</span><span style=\"color: orange;\">D</span></th></tr>\n<tr><td>10.</td><th><span style=\"color: red;\">A</span><span style=\"color: black;\">E</span><span style=\"color: blue;\">B</span></th><th></th><td>22.</td><th><span style=\"color: blue;\">B</span><span style=\"color: black;\">E</span><span style=\"color: red;\">A</span></th><th></th><td>34.</td><th><span style=\"color: green;\">C</span><span style=\"color: black;\">E</span><span style=\"color: red;\">A</span></th><th></th><td>46.</td><th><span style=\"color: orange;\">D</span><span style=\"color: black;\">E</span><span style=\"color: red;\">A</span></th><th></th><td>58.</td><th><span style=\"color: black;\">E</span><span style=\"color: orange;\">D</span><span style=\"color: red;\">A</span></th></tr>\n<tr><td>11.</td><th><span style=\"color: red;\">A</span><span style=\"color: black;\">E</span><span style=\"color: green;\">C</span></th><th></th><td>23.</td><th><span style=\"color: blue;\">B</span><span style=\"color: black;\">E</span><span style=\"color: green;\">C</span></th><th></th><td>35.</td><th><span style=\"color: green;\">C</span><span style=\"color: black;\">E</span><span style=\"color: blue;\">B</span></th><th></th><td>47.</td><th><span style=\"color: orange;\">D</span><span style=\"color: black;\">E</span><span style=\"color: blue;\">B</span></th><th></th><td>59.</td><th><span style=\"color: black;\">E</span><span style=\"color: orange;\">D</span><span style=\"color: blue;\">B</span></th></tr>\n<tr><td>12.</td><th><span style=\"color: red;\">A</span><span style=\"color: black;\">E</span><span style=\"color: orange;\">D</span></th><th></th><td>24.</td><th><span style=\"color: blue;\">B</span><span style=\"color: black;\">E</span><span style=\"color: orange;\">D</span></th><th></th><td>36.</td><th><span style=\"color: green;\">C</span><span style=\"color: black;\">E</span><span style=\"color: orange;\">D</span></th><th></th><td>48.</td><th><span style=\"color: orange;\">D</span><span style=\"color: black;\">E</span><span style=\"color: green;\">C</span></th><th></th><td>60.</td><th><span style=\"color: black;\">E</span><span style=\"color: orange;\">D</span><span style=\"color: green;\">C</span></th></tr>\n</table>\n</div>\n</div>\n<div class=\"show_next ks_button\">pokaż dalej</div>\n<div class=\"show_step\">\n<p>\n                        Teraz przyjrzyj się wariacjom o numerach 1, 4, 13, 16, 25 i 28:\n                    </p>\n<div class=\"table_wrapper\">\n<table class=\"my_table_noborder\">\n<tr>\n<td>1.</td><th><span style=\"color: red;\">A</span><span style=\"color: blue;\">B</span><span style=\"color: green;\">C</span></th>\n<td>13.</td><th><span style=\"color: blue;\">B</span><span style=\"color: red;\">A</span><span style=\"color: green;\">C</span></th>\n<td>25.</td><th><span style=\"color: green;\">C</span><span style=\"color: red;\">A</span><span style=\"color: blue;\">B</span></th>\n</tr>\n<tr>\n<td>4.</td><th><span style=\"color: red;\">A</span><span style=\"color: green;\">C</span><span style=\"color: blue;\">B</span></th>\n<td>16.</td><th><span style=\"color: blue;\">B</span><span style=\"color: green;\">C</span><span style=\"color: red;\">A</span></th>\n<td>28.</td><th><span style=\"color: green;\">C</span><span style=\"color: blue;\">B</span><span style=\"color: red;\">A</span></th>\n</tr>\n</table>\n</div>\n</div>\n<div class=\"show_next ks_button\">pokaż dalej</div>\n<div class=\"show_step\">\n<p>\n                        Te wariacje różnią się kolejnością, ale składają się z tych samych elementów. A my chcieliśmy tylko\n                    </p>\n<blockquote>\n                        \"wybrać trzy obiekty spośród pięciu\",\n                    </blockquote>\n<p>\n                        ich <strong>kolejność</strong> jest dla nas <strong>bez znaczenia</strong>.\n                    </p>\n</div>\n<div class=\"show_next ks_button\">pokaż dalej</div>\n<div class=\"show_step\">\n<p>\n                        I dlatego te <strong>sześć</strong> wariacji to tylko jeden wybór - trzech elementów: <span style=\"color: red; font-weight: bold;\">A</span>, <span style=\"color: blue; font-weight: bold;\">B</span> i <span style=\"color: green; font-weight: bold;\">C</span>.\n                    </p>\n</div>\n<div class=\"show_next ks_button\">pokaż dalej</div>\n<div class=\"show_step\">\n<p>\n                        Podobnie dla każdego innego wyboru <strong>trzech</strong> elementów mamy <strong>sześć</strong> wariacji.\n                    </p>\n<p>\n                        Wyborów jest więc sześciokrotnie mniej, czyli \\(60:6=10\\).\n                    </p>\n</div>\n<div class=\"show_next ks_button\">pokaż dalej</div>\n<div class=\"show_step\">\n<p>\n                        Ale dlaczego akurat sześciokrotnie mniej?\n                    </p>\n<p>\n                        Dlatego, że dowolne trzy elementy możemy ustawić w kolejności na \\(3!=6\\) sposobów.\n                    </p>\n</div>\n<div class=\"show_next ks_button\">pokaż dalej</div>\n<div class=\"show_step\">\n<p>\n                        Podsumujmy. Jak znaleźć liczbę możliwych wyborów trzech elementów z pięciu?\n                    </p>\n<p>\n                        Najpierw policzyliśmy liczbę wariacji bez powtórzeń:\n                    </p>\n                    \\[\n                    \\frac{5!}{(5-3)!}\n                    \\]\n                    <p>\n                        a potem tę liczbę podzieliliśmy przez \\(3!\\):\n                    </p>\n                    \\[\n                    \\frac{5!}{(5-3)!}:3!=\\frac{5!}{(5-3)!}\\cdot\\frac{1}{3!}=\\frac{5!}{(5-3)!\\cdot 3!}\n                    \\]\n                </div>\n</div>\n"
    },
    {
      "type": "text",
      "body": "<h3>Ważne wnioski</h3>"
    },
    {
      "type": "text",
      "body": "<ol class=\"bold\">\n<li>\n            Musimy odróżniać, <strong>kiedy kolejność wybieranych obiektów ma znaczenie, a kiedy nie</strong>.\n            <details class=\"ks_example\">\n<!-- <summary><p class=\"example\" style=\"display: inline-block!important;\"></p></summary> -->\n<summary class=\"example\"></summary>\n                Pomyśl o dwóch przypadkach:\n                <ol class=\"bold\" type=\"I\">\n<li>\n                        Z klasy wybieramy przewodniczącego i skarbnika.\n                    </li>\n<li>\n                        Z klasy wybieramy dwuosobową delegację.\n                    </li>\n</ol>\n<p>\n                    Widzisz różnicę?\n                </p>\n<ol class=\"bold\" type=\"I\">\n<li>\n                        Z klasy wybieramy przewodniczącego i skarbnika.\n                        <hr/>\n                        Tu kolejność ma znaczenie, bo role wybranych osób są odmienne. Wybory:\n                        <ul class=\"nolist\">\n<li>\n                                Osoba <strong>A</strong> - przewodniczący, osoba <strong>B</strong> - skarbnik,\n                            </li>\n<li>\n                                Osoba <strong>B</strong> - przewodniczący, osoba <strong>A</strong> - skarbnik,\n                            </li>\n</ul>\n                        są różne.\n                        <hr/>\n</li>\n<li>\n                        Z klasy wybieramy dwuosobową delegację.\n                        <hr/>\n                        Tu kolejność nie ma znaczenia. Wybory:\n                        <ul class=\"nolist\">\n<li>\n                                Osoba <strong>A</strong> - członek delegacji, osoba <strong>B</strong> - członek delegacji,\n                            </li>\n<li>\n                                Osoba <strong>B</strong> - członek delegacji, osoba <strong>A</strong> - członek delegacji,\n                            </li>\n</ul>\n                        niczym się nie różnią.\n                        <hr/>\n</li>\n</ol>\n</details>\n</li>\n<li>\n            Warto ustalić prosty <strong>sposób obliczania liczby możliwych wyborów, gdy kolejność nie ma znaczenia</strong>.\n            <details class=\"ks_example\">\n<summary class=\"question_like\">Wzór</summary>\n<p>\n                    Ustaliliśmy, że gdy wybieramy <strong>trzy</strong> obiekty z <strong>pięciu</strong>, to możliwości jest\n                </p>\n                \\[\n                \\frac{5!}{3!\\cdot(5-3)!}=10\n                \\]\n                <p>\n                    Analogicznie, gdy wybieramy <strong>\\(k\\)</strong> obiektów spośród <strong>\\(n\\)</strong> obiektów, możliwości jest\n                </p>\n                \\[\n                \\frac{n!}{k!(n-k)!}\n                \\]\n                <p>\n                    I tym wzorem teraz się zajmiemy.\n                </p>\n</details>\n</li>\n</ol>"
    }
  ],
  "fully_mapped": true,
  "seed_hash": "35d30ab05846e1d1f5fe17b9b611ab446190191a74411eadca8f837e58bbbecb"
}